odoo/addons/product_supplierinfo_group_intercompany/README.rst
odoo/addons/product_supplierinfo_group_intercompany/__init__.py
odoo/addons/product_supplierinfo_group_intercompany/__manifest__.py
odoo/addons/product_supplierinfo_group_intercompany/hook.py
odoo/addons/product_supplierinfo_group_intercompany/i18n/it.po
odoo/addons/product_supplierinfo_group_intercompany/i18n/product_supplierinfo_group_intercompany.pot
odoo/addons/product_supplierinfo_group_intercompany/migrations/14.0.1.1.0/post-fix-data.py
odoo/addons/product_supplierinfo_group_intercompany/models/__init__.py
odoo/addons/product_supplierinfo_group_intercompany/models/product_intercompany_supplier_mixin.py
odoo/addons/product_supplierinfo_group_intercompany/models/product_pricelist.py
odoo/addons/product_supplierinfo_group_intercompany/models/product_supplierinfo.py
odoo/addons/product_supplierinfo_group_intercompany/models/product_supplierinfo_group.py
odoo/addons/product_supplierinfo_group_intercompany/readme/CONTRIBUTORS.rst
odoo/addons/product_supplierinfo_group_intercompany/readme/DESCRIPTION.rst
odoo/addons/product_supplierinfo_group_intercompany/readme/ROADMAP.rst
odoo/addons/product_supplierinfo_group_intercompany/readme/USAGE.rst
odoo/addons/product_supplierinfo_group_intercompany/security/ir_rule.xml
odoo/addons/product_supplierinfo_group_intercompany/static/description/icon.png
odoo/addons/product_supplierinfo_group_intercompany/static/description/index.html
odoo/addons/product_supplierinfo_group_intercompany/tests/__init__.py
odoo/addons/product_supplierinfo_group_intercompany/tests/test_product_supplerinfo_group.py
odoo/addons/product_supplierinfo_group_intercompany/views/product_pricelist.xml
odoo/addons/product_supplierinfo_group_intercompany/views/product_supplierinfo_group.xml
odoo14_addon_product_supplierinfo_group_intercompany-14.0.1.1.3.dist-info/METADATA
odoo14_addon_product_supplierinfo_group_intercompany-14.0.1.1.3.dist-info/WHEEL
odoo14_addon_product_supplierinfo_group_intercompany-14.0.1.1.3.dist-info/top_level.txt
odoo14_addon_product_supplierinfo_group_intercompany-14.0.1.1.3.dist-info/RECORD
