Metadata-Version: 2.1
Name: odoo14-addon-product-supplierinfo-group-intercompany
Version: 14.0.1.1.3
Summary: Add sequence field on grouped pricelist items
Home-page: https://github.com/OCA/multi-company
Author: Akretion,Odoo Community Association (OCA)
Author-email: support@odoo-community.org
License: AGPL-3
Platform: UNKNOWN
Classifier: Programming Language :: Python
Classifier: Framework :: Odoo
Classifier: Framework :: Odoo :: 14.0
Classifier: License :: OSI Approved :: GNU Affero General Public License v3
Requires-Python: >=3.6
Requires-Dist: odoo14-addon-product-supplierinfo-group
Requires-Dist: odoo14-addon-product-supplierinfo-intercompany
Requires-Dist: odoo <14.1dev,>=14.0a
